swtMCP/__init__.py
swtmcp-0.1.1.dist-info/METADATA
swtmcp-0.1.1.dist-info/WHEEL
swtmcp-0.1.1.dist-info/RECORD
