Metadata-Version: 2.4
Name: swtMCP
Version: 0.1.1
Summary: A package for credit risk modeling with various tools.
Requires-Python: >=3.11.9
Requires-Dist: mcp[cli]>=1.10.1
Requires-Dist: openai
Requires-Dist: requests
Requires-Dist: sklearn
